README.rst
setup.py
example/__init__.py
example/manage.py
example/models.py
example/runserver.py
example/settings.py
example/activities/__init__.py
zengine/__init__.py
zengine/client_queue.py
zengine/config.py
zengine/current.py
zengine/engine.py
zengine/log.py
zengine/management_commands.py
zengine/middlewares.py
zengine/receivers.py
zengine/settings.py
zengine/signals.py
zengine/wf_daemon.py
zengine.egg-info/PKG-INFO
zengine.egg-info/SOURCES.txt
zengine.egg-info/dependency_links.txt
zengine.egg-info/requires.txt
zengine.egg-info/top_level.txt
zengine/auth/__init__.py
zengine/auth/auth_backend.py
zengine/auth/permissions.py
zengine/diagrams/assign_same_abstract_role.bpmn
zengine/diagrams/change_language.bpmn
zengine/diagrams/channel_management.bpmn
zengine/diagrams/crud.bpmn
zengine/diagrams/edit_catalog_data.bpmn
zengine/diagrams/login.bpmn
zengine/diagrams/logout.bpmn
zengine/diagrams/not_found.bpmn
zengine/diagrams/permissions.bpmn
zengine/diagrams/postpone_workflow.bpmn
zengine/diagrams/role_switching.bpmn
zengine/diagrams/suspend_workflow.bpmn
zengine/diagrams/task_assign_yourself.bpmn
zengine/dispatch/__init__.py
zengine/dispatch/dispatcher.py
zengine/dispatch/weakref_backports.py
zengine/forms/__init__.py
zengine/forms/fields.py
zengine/forms/json_form.py
zengine/forms/model_form.py
zengine/lib/__init__.py
zengine/lib/cache.py
zengine/lib/camunda_bpmn_packager.py
zengine/lib/camunda_parser.py
zengine/lib/catalog_data.py
zengine/lib/concurrent_amqp_test_client.py
zengine/lib/decorators.py
zengine/lib/exceptions.py
zengine/lib/json_interface.py
zengine/lib/test_utils.py
zengine/lib/translation.py
zengine/lib/utils.py
zengine/lib/wf_initial_values.py
zengine/messaging/__init__.py
zengine/messaging/lib.py
zengine/messaging/model.py
zengine/messaging/permissions.py
zengine/messaging/views.py
zengine/models/__init__.py
zengine/models/auth.py
zengine/models/workflow_manager.py
zengine/tornado_server/__init__.py
zengine/tornado_server/get_logger.py
zengine/tornado_server/server.py
zengine/tornado_server/ws_to_queue.py
zengine/views/__init__.py
zengine/views/auth.py
zengine/views/base.py
