Metadata-Version: 1.0
Name: zengine
Version: 0.8.3
Summary: BPMN workflow based web service framework with advanced permissions and extensible CRUD features
Home-page: https://github.com/zetaops/zengine
Author: Zetaops AS
Author-email: info@zetaops.io
License: GPL v3
Keywords: web,framework,rest,service,json,bpmn,workflow,web service,orm,nosql,bpmn 2,crud,scaffolding
Platform: UNKNOWN
